liblineage/__init__.py
liblineage/constants/__init__.py
liblineage/constants/infra.py
liblineage/constants/versions.py
liblineage/device.py
liblineage/hudson/__init__.py
liblineage/hudson/build_target.py
liblineage/hudson/period.py
liblineage/ota/__init__.py
liblineage/ota/full_update_info.py
liblineage/updater/__init__.py
liblineage/updater/http_utils.py
liblineage/updater/v1/__init__.py
liblineage/updater/v1/_deserializer.py
liblineage/updater/v1/build.py
liblineage/updater/v2/__init__.py
liblineage/updater/v2/_deserializer.py
liblineage/updater/v2/build.py
liblineage/updater/v2/build_file.py
liblineage/updater/v2/device.py
liblineage/updater/v2/oem.py
liblineage/updater/v2/oem_device.py
liblineage/wiki/__init__.py
liblineage/wiki/data_types/__init__.py
liblineage/wiki/data_types/architecture_data.py
liblineage/wiki/data_types/base_data.py
liblineage/wiki/data_types/battery_data.py
liblineage/wiki/data_types/bluetooth_data.py
liblineage/wiki/data_types/camera_data.py
liblineage/wiki/data_types/dimension_data.py
liblineage/wiki/data_types/kernel_data.py
liblineage/wiki/data_types/network_data.py
liblineage/wiki/data_types/peripherals_data.py
liblineage/wiki/data_types/release_data.py
liblineage/wiki/data_types/screen_data.py
liblineage/wiki/data_types/sdcard_data.py
liblineage/wiki/device_data.py
liblineage-1.6.0.dist-info/METADATA
liblineage-1.6.0.dist-info/WHEEL
liblineage-1.6.0.dist-info/RECORD
